kendall_w/__init__.py
kendall_w/kendall_w.py
kendall_w-1.0.0.dist-info/LICENSE.md
kendall_w-1.0.0.dist-info/METADATA
kendall_w-1.0.0.dist-info/WHEEL
kendall_w-1.0.0.dist-info/top_level.txt
kendall_w-1.0.0.dist-info/RECORD
