Metadata-Version: 2.1
Name: kendall-w
Version: 1.0.0
Summary: Computes Kendall's coefficient of concordance
Home-page: https://github.com/ugolbck/kendall-w
Author: Ugo Loobuyck
Author-email: ugo.loobuyck@gmail.com
License: BSD
Download-URL: https://github.com/ugolbck/kendall-w/tarball/1.0.0
Keywords: kendall,annotator,agreement,rank,metric
Platform: UNKNOWN
Classifier: Development Status :: 5 - Production/Stable
Classifier: Intended Audience :: Developers
Classifier: Programming Language :: Python :: 3
Classifier: Programming Language :: Python :: 3.5
Classifier: Programming Language :: Python :: 3.6
Classifier: Programming Language :: Python :: 3.7
Classifier: Programming Language :: Python :: 3.8
Classifier: Topic :: Scientific/Engineering :: Mathematics
